LICENSE
README.md
setup.py
geo_map_harmonizer.egg-info/PKG-INFO
geo_map_harmonizer.egg-info/SOURCES.txt
geo_map_harmonizer.egg-info/dependency_links.txt
geo_map_harmonizer.egg-info/requires.txt
geo_map_harmonizer.egg-info/top_level.txt
geomapharmonizer/__init__.py
geomapharmonizer/handler.py
geomapharmonizer/src/__init__.py
geomapharmonizer/src/utils.py