Metadata-Version: 2.1
Name: geo-map-harmonizer
Version: 0.0.0.2
Summary: Algorithm for harmonizing geotiff map legends
Author: Sabrina G Marques
Author-email: sabrina.marques@unesp.br
License: MIT License
Keywords: gdal geoespacial LULC
Requires-Python: >=3.9
License-File: LICENSE
